ratelimiter/__init__.py
ratelimiter/limiter.py
tests/__init__.py
tests/test_rate_limiter.py
redis_leakybucket_rate_limiter-1.0.1.dist-info/METADATA
redis_leakybucket_rate_limiter-1.0.1.dist-info/WHEEL
redis_leakybucket_rate_limiter-1.0.1.dist-info/top_level.txt
redis_leakybucket_rate_limiter-1.0.1.dist-info/RECORD
